Metadata-Version: 2.3
Name: swarmauri_tokens_jwt
Version: 0.3.0.dev4
Summary: JWT token service for Swarmauri
License: Apache-2.0
Author: Swarmauri
Author-email: opensource@swarmauri.com
Requires-Python: >=3.10,<3.13
Classifier: License :: OSI Approved :: Apache Software License
Classifier: Programming Language :: Python :: 3.10
Classifier: Programming Language :: Python :: 3.11
Classifier: Programming Language :: Python :: 3.12
Provides-Extra: ecdsa
Provides-Extra: eddsa
Provides-Extra: hmac
Provides-Extra: rsa
Requires-Dist: cryptography ; extra == "ecdsa"
Requires-Dist: cryptography ; extra == "eddsa"
Requires-Dist: cryptography ; extra == "rsa"
Requires-Dist: swarmauri_base
Requires-Dist: swarmauri_core
Requires-Dist: swarmauri_signing_jws
